boundbox/BoundBox_class.py
boundbox/BoundBox_utils.py
boundbox/Exceptions.py
boundbox/Line_class.py
boundbox/Point_class.py
boundbox/__init__.py
boundbox-0.0.5.dist-info/LICENSE
boundbox-0.0.5.dist-info/METADATA
boundbox-0.0.5.dist-info/WHEEL
boundbox-0.0.5.dist-info/top_level.txt
boundbox-0.0.5.dist-info/RECORD
