Metadata-Version: 2.1
Name: boundbox
Version: 0.0.5
Summary: Package for bounding boxes
Home-page: https://github.com/akash1729/boundbox
Author: Akash Thomas
Author-email: akashthomasjohn@gmail.com
License: UNKNOWN
Platform: UNKNOWN
Classifier: Programming Language :: Python :: 3
Classifier: License :: OSI Approved :: MIT License
Classifier: Operating System :: OS Independent
Requires-Python: >=3.6
License-File: LICENSE
